pytypeutil/__init__.py
pytypeutil/_const.py
pytypeutil/_error.py
pytypeutil/_function.py
pytypeutil/_typecode.py
pytypeutil/checker/__init__.py
pytypeutil/checker/_bool.py
pytypeutil/checker/_checker.py
pytypeutil/checker/_common.py
pytypeutil/checker/_datetime.py
pytypeutil/checker/_dictionary.py
pytypeutil/checker/_infinity.py
pytypeutil/checker/_integer.py
pytypeutil/checker/_interface.py
pytypeutil/checker/_nan.py
pytypeutil/checker/_none.py
pytypeutil/checker/_realnumber.py
pytypeutil/checker/_string.py
pytypeutil/converter/__init__.py
pytypeutil/converter/_bool.py
pytypeutil/converter/_common.py
pytypeutil/converter/_datetime.py
pytypeutil/converter/_dictionary.py
pytypeutil/converter/_integer.py
pytypeutil/converter/_interface.py
pytypeutil/converter/_nop.py
pytypeutil/converter/_realnumber.py
pytypeutil/converter/_string.py
pytypeutil/type/__init__.py
pytypeutil/type/_base.py
pytypeutil/type/_bool.py
pytypeutil/type/_datetime.py
pytypeutil/type/_dictionary.py
pytypeutil/type/_infinity.py
pytypeutil/type/_integer.py
pytypeutil/type/_nan.py
pytypeutil/type/_none.py
pytypeutil/type/_realnumber.py
pytypeutil/type/_string.py
pytypeutil-0.0.1.dist-info/DESCRIPTION.rst
pytypeutil-0.0.1.dist-info/METADATA
pytypeutil-0.0.1.dist-info/RECORD
pytypeutil-0.0.1.dist-info/WHEEL
pytypeutil-0.0.1.dist-info/metadata.json
pytypeutil-0.0.1.dist-info/top_level.txt
