Metadata-Version: 2.0
Name: pytypeutil
Version: 0.0.1
Summary: A python library for variable type checker/validator/converter at run time.
Requires-Dist: mbstrdecoder (>=0.2.1)
Requires-Dist: python-dateutil (>=2.6.0)
Requires-Dist: pytz (>=2016.10)
Requires-Dist: six (>=1.10)
